alu_without_errors.v
module alu(
           input [7:0] A,B,                  
           input [3:0] ALU_Sel,
           output [7:0] ALU_Out, 
           output CarryOut // Carry Out Flag
    );
    reg [7:0] ALU_Result;
    wire [8:0] tmp;
    assign ALU_Out = ALU_Result;
    assign tmp = {1'b0,A} + {1'b0,B};
    assign CarryOut = tmp[8]; // Carryout flag
    always @(*) begin  
        case(ALU_Sel)
        4'b0000: 
           ALU_Result = A + B ; 
        4'b0001: 
           ALU_Result = A - B ;
        4'b0010:
           ALU_Result = A * B;
        4'b0011: 
           ALU_Result = A/B;
        4'b0100: 
           ALU_Result = A<<1;
         4'b0101:
           ALU_Result = A>>1;
         4'b0110: 
           ALU_Result = {A[6:0],A[7]};
         4'b0111:
           ALU_Result = {A[0],A[7:1]};
          4'b1000:
           ALU_Result = A & B;
          4'b1001: 
           ALU_Result = A | B;
          4'b1010: 
           ALU_Result = A ^ B;
          4'b1011:
           ALU_Result = ~(A | B);
          4'b1100:
           ALU_Result = ~(A & B);
          4'b1101: 
           ALU_Result = ~(A ^ B);
          4'b1110: 
           ALU_Result = (A>B)?8'd1:8'd0 ;
          4'b1111: 
           ALU_Result = (A==B)?8'd1:8'd0 ;
          default: ALU_Result = A + B ;
  endcase
  end
endmodule

`timescale 1ns / 1ps  

module tb_alu;
 reg [7:0] A;
 wire CarryOut;
 reg [3:0] ALU_Sel;

 wire [7:0] ALU_Out;
 reg [7:0] B;
 integer i;
	alu test_uut(
            A,B,                   
            ALU_Sel,
            ALU_Out, 
            CarryOut // Carry Out Flag
     );
    initial begin
        $dumpfile("alua.vcd");
        $dumpvars(0, tb_alu);
        A = 8'h0A;
        B = 8'h02;
        ALU_Sel = 4'h0;

        for (i=0;i<=15;i=i+1)
        begin
        ALU_Sel = ALU_Sel + 8'h01;
        #10;
end;
        
        A = 8'hF6;
        B = 8'h0A;
end
endmodule

alua.vcd
$date
	Thu Feb 16 00:42:24 2023
$end
$version
	Icarus Verilog
$end
$timescale
	1ps
$end
$scope module tb_alu $end
$var wire 1 ! CarryOut $end
$var wire 8 " ALU_Out [7:0] $end
$var reg 8 # A [7:0] $end
$var reg 4 $ ALU_Sel [3:0] $end
$var reg 8 % B [7:0] $end
$var integer 32 & i [31:0] $end
$scope module test_uut $end
$var wire 8 ' A [7:0] $end
$var wire 8 ( ALU_Out [7:0] $end
$var wire 4 ) ALU_Sel [3:0] $end
$var wire 8 * B [7:0] $end
$var wire 9 + tmp [8:0] $end
$var wire 1 ! CarryOut $end
$var reg 8 , ALU_Result [7:0] $end
$upscope $end
$upscope $end
$enddefinitions $end
#0
$dumpvars
b1000 ,
b1100 +
b10 *
b1 )
b1000 (
b1010 '
b0 &
b10 %
b1 $
b1010 #
b1000 "
0!
$end
#10000
b10100 "
b10100 (
b10100 ,
b10 $
b10 )
b1 &
#20000
b101 "
b101 (
b101 ,
b11 $
b11 )
b10 &
#30000
b10100 "
b10100 (
b10100 ,
b100 $
b100 )
b11 &
#40000
b101 "
b101 (
b101 ,
b101 $
b101 )
b100 &
#50000
b10100 "
b10100 (
b10100 ,
b110 $
b110 )
b101 &
#60000
b101 "
b101 (
b101 ,
b111 $
b111 )
b110 &
#70000
b10 "
b10 (
b10 ,
b1000 $
b1000 )
b111 &
#80000
b1010 "
b1010 (
b1010 ,
b1001 $
b1001 )
b1000 &
#90000
b1000 "
b1000 (
b1000 ,
b1010 $
b1010 )
b1001 &
#100000
b11110101 "
b11110101 (
b11110101 ,
b1011 $
b1011 )
b1010 &
#110000
b11111101 "
b11111101 (
b11111101 ,
b1100 $
b1100 )
b1011 &
#120000
b11110111 "
b11110111 (
b11110111 ,
b1101 $
b1101 )
b1100 &
#130000
b1 "
b1 (
b1 ,
b1110 $
b1110 )
b1101 &
#140000
b0 "
b0 (
b0 ,
b1111 $
b1111 )
b1110 &
#150000
b1100 "
b1100 (
b1100 ,
b0 $
b0 )
b1111 &
#160000
1!
b0 "
b0 (
b0 ,
b1010 %
b1010 *
b100000000 +
b11110110 #
b11110110 '
b10000 &
