fulladder.v
module fulladder(d1,d2,cin,sumout,cout);
	input d1,d2,cin;
	output sumout,cout;
	wire a1,a2,a3;
xor u1(a1,d1,d2);
and u2(a2,d1,d2);
and u3(a3,a1,cin);
or u4(cout,a2,a3);
xor u5(sumout,a1,cin);
endmodule

fulladder_tb.v
module tb_fulladder;
reg d0,d1,cin0;
wire sumout0,cout0;
fulladder adder2 (d0,d1,cin0,sumout0,cout0);
initial
begin
	$dumpfile("fulladder_out.vcd");
	$dumpvars(0,tb_fulladder);

	d0=0;
	d1=0;
	cin0=0;
	#10;
	d0=0;	d1=0;	cin0=1;	#5;
	d0=0;	d1=1;	cin0=0;	#5;
	d0=0;	d1=1;	cin0=1;	#5;
	d0=1;	d1=0;	cin0=0;	#5;
	d0=1;	d1=0;	cin0=1;	#5;
	d0=1;	d1=1;	cin0=0;	#5;
	d0=1;	d1=1;	cin0=1;	#5;
end
endmodule

fulladder_out.vcd
$date
	Fri Jan 20 14:22:06 2023
$end
$version
	Icarus Verilog
$end
$timescale
	1s
$end
$scope module tb_fulladder $end
$var wire 1 ! sumout0 $end
$var wire 1 " cout0 $end
$var reg 1 # cin0 $end
$var reg 1 $ d0 $end
$var reg 1 % d1 $end
$scope module adder2 $end
$var wire 1 & a1 $end
$var wire 1 ' a2 $end
$var wire 1 ( a3 $end
$var wire 1 # cin $end
$var wire 1 " cout $end
$var wire 1 $ d1 $end
$var wire 1 % d2 $end
$var wire 1 ! sumout $end
$upscope $end
$upscope $end
$enddefinitions $end
#0
$dumpvars
0(
0'
0&
0%
0$
0#
0"
0!
$end
#10
1!
1#
#15
1&
0#
1%
#20
1"
1(
0!
1#
#25
0"
0(
1!
0#
0%
1$
#30
1"
1(
0!
1#
#35
0(
0&
1'
0#
1%
#40
1!
1#
