mux2.v
module mux2(in0,in1,select,out);
	input in0,in1,select;
	output out;
	wire s0,w0,w1;

	not n1(s0,select);
	and a1(w0,s0,in0);
	and a2(w1,select,in1);
	or g3(out,w0,w1);
endmodule

mux4.v
module mux4(in0,in1,in2,in3,select1,select2,out);
	input in0,in1,in2,in3,select1,select2;
       output out;
	wire  w0,w1;
	mux2 a1(in0,in1,select1,w0);
	mux2 a2(in2,in3,select1,w1);
	mux2 output_1(w0,w1,select2,out);
endmodule

mux4_tb.v
module tb_mux4;
reg d0;
reg d1;
reg d2;
reg d3;
reg sel1;
reg sel2;
wire Data_out;
mux4 namexyz1(d0,d1,d2,d3,sel1,sel2,Data_out);
initial
begin
	$dumpfile("mux4_out.vcd");
	$dumpvars(0,tb_mux4);
	d0=0;
	d1=0;
	d2=0;
	d3=0;
	sel1=0;
	sel2=0;
	#10;

	d0=0;	d1=0;	d2=0;	d3=0;	sel1=0;	sel2=1;	#10;
	d0=0;	d1=0;	d2=0;	d3=0;	sel1=1;	sel2=0;	#10;
	d0=0;	d1=0;	d2=0;	d3=0;	sel1=1;	sel2=1;	#10;
	d0=0;	d1=0;	d2=0;	d3=1;	sel1=0;	sel2=0;	#10;
	d0=0;	d1=0;	d2=0;	d3=1;	sel1=0;	sel2=1;	#10;
	d0=0;	d1=0;	d2=0;	d3=1;	sel1=1;	sel2=0;	#10;
	d0=0;	d1=0;	d2=0;	d3=1;	sel1=1;	sel2=1;	#10;
	d0=0;	d1=0;	d2=1;	d3=0;	sel1=0;	sel2=0;	#10;
	d0=0;	d1=0;	d2=1;	d3=0;	sel1=0;	sel2=1;	#10;
	d0=0;	d1=0;	d2=1;	d3=0;	sel1=1;	sel2=0;	#10;
	d0=0;	d1=0;	d2=1;	d3=0;	sel1=1;	sel2=1;	#10;
	d0=0;	d1=0;	d2=1;	d3=1;	sel1=0;	sel2=0;	#10;
	d0=0;	d1=0;	d2=1;	d3=1;	sel1=0;	sel2=1;	#10;
	d0=0;	d1=0;	d2=1;	d3=1;	sel1=1;	sel2=0;	#10;
	d0=0;	d1=0;	d2=1;	d3=1;	sel1=1;	sel2=1;	#10;
	d0=0;	d1=1;	d2=0;	d3=0;	sel1=0;	sel2=0;	#10;
	d0=0;	d1=1;	d2=0;	d3=0;	sel1=0;	sel2=1;	#10;
	d0=0;	d1=1;	d2=0;	d3=0;	sel1=1;	sel2=0;	#10;
	d0=0;	d1=1;	d2=0;	d3=0;	sel1=1;	sel2=1;	#10;
	d0=0;	d1=1;	d2=0;	d3=1;	sel1=0;	sel2=0;	#10;
	d0=0;	d1=1;	d2=0;	d3=1;	sel1=0;	sel2=1;	#10;
	d0=0;	d1=1;	d2=0;	d3=1;	sel1=1;	sel2=0;	#10;
	d0=0;	d1=1;	d2=0;	d3=1;	sel1=1;	sel2=1;	#10;
	d0=0;	d1=1;	d2=1;	d3=0;	sel1=0;	sel2=0;	#10;
	d0=0;	d1=1;	d2=1;	d3=0;	sel1=0;	sel2=1;	#10;
	d0=0;	d1=1;	d2=1;	d3=0;	sel1=1;	sel2=0;	#10;
	d0=0;	d1=1;	d2=1;	d3=0;	sel1=1;	sel2=1;	#10;
	d0=0;	d1=1;	d2=1;	d3=1;	sel1=0;	sel2=0;	#10;
	d0=0;	d1=1;	d2=1;	d3=1;	sel1=0;	sel2=1;	#10;
	d0=0;	d1=1;	d2=1;	d3=1;	sel1=1;	sel2=0;	#10;
	d0=0;	d1=1;	d2=1;	d3=1;	sel1=1;	sel2=1;	#10;
	d0=1;	d1=0;	d2=0;	d3=0;	sel1=0;	sel2=0;	#10;
	d0=1;	d1=0;	d2=0;	d3=0;	sel1=0;	sel2=1;	#10;
	d0=1;	d1=0;	d2=0;	d3=0;	sel1=1;	sel2=0;	#10;
	d0=1;	d1=0;	d2=0;	d3=0;	sel1=1;	sel2=1;	#10;
	d0=1;	d1=0;	d2=0;	d3=1;	sel1=0;	sel2=0;	#10;
	d0=1;	d1=0;	d2=0;	d3=1;	sel1=0;	sel2=1;	#10;
	d0=1;	d1=0;	d2=0;	d3=1;	sel1=1;	sel2=0;	#10;
	d0=1;	d1=0;	d2=0;	d3=1;	sel1=1;	sel2=1;	#10;
	d0=1;	d1=0;	d2=1;	d3=0;	sel1=0;	sel2=0;	#10;
	d0=1;	d1=0;	d2=1;	d3=0;	sel1=0;	sel2=1;	#10;
	d0=1;	d1=0;	d2=1;	d3=0;	sel1=1;	sel2=0;	#10;
	d0=1;	d1=0;	d2=1;	d3=0;	sel1=1;	sel2=1;	#10;
	d0=1;	d1=0;	d2=1;	d3=1;	sel1=0;	sel2=0;	#10;
	d0=1;	d1=0;	d2=1;	d3=1;	sel1=0;	sel2=1;	#10;
	d0=1;	d1=0;	d2=1;	d3=1;	sel1=1;	sel2=0;	#10;
	d0=1;	d1=0;	d2=1;	d3=1;	sel1=1;	sel2=1;	#10;
	d0=1;	d1=1;	d2=0;	d3=0;	sel1=0;	sel2=0;	#10;
	d0=1;	d1=1;	d2=0;	d3=0;	sel1=0;	sel2=1;	#10;
	d0=1;	d1=1;	d2=0;	d3=0;	sel1=1;	sel2=0;	#10;
	d0=1;	d1=1;	d2=0;	d3=0;	sel1=1;	sel2=1;	#10;
	d0=1;	d1=1;	d2=0;	d3=1;	sel1=0;	sel2=0;	#10;
	d0=1;	d1=1;	d2=0;	d3=1;	sel1=0;	sel2=1;	#10;
	d0=1;	d1=1;	d2=0;	d3=1;	sel1=1;	sel2=0;	#10;
	d0=1;	d1=1;	d2=0;	d3=1;	sel1=1;	sel2=1;	#10;
	d0=1;	d1=1;	d2=1;	d3=0;	sel1=0;	sel2=0;	#10;
	d0=1;	d1=1;	d2=1;	d3=0;	sel1=0;	sel2=1;	#10;
	d0=1;	d1=1;	d2=1;	d3=0;	sel1=1;	sel2=0;	#10;
	d0=1;	d1=1;	d2=1;	d3=0;	sel1=1;	sel2=1;	#10;
	d0=1;	d1=1;	d2=1;	d3=1;	sel1=0;	sel2=0;	#10;
	d0=1;	d1=1;	d2=1;	d3=1;	sel1=0;	sel2=1;	#10;
	d0=1;	d1=1;	d2=1;	d3=1;	sel1=1;	sel2=0;	#10;
	d0=1;	d1=1;	d2=1;	d3=1;	sel1=1;	sel2=1;	#10;
end
endmodule

mux4_out.vcd
$date
	Fri Jan 20 14:27:11 2023
$end
$version
	Icarus Verilog
$end
$timescale
	1s
$end
$scope module tb_mux4 $end
$var wire 1 ! Data_out $end
$var reg 1 " d0 $end
$var reg 1 # d1 $end
$var reg 1 $ d2 $end
$var reg 1 % d3 $end
$var reg 1 & sel1 $end
$var reg 1 ' sel2 $end
$scope module namexyz1 $end
$var wire 1 " in0 $end
$var wire 1 # in1 $end
$var wire 1 $ in2 $end
$var wire 1 % in3 $end
$var wire 1 & select1 $end
$var wire 1 ' select2 $end
$var wire 1 ( w1 $end
$var wire 1 ) w0 $end
$var wire 1 ! out $end
$scope module a1 $end
$var wire 1 " in0 $end
$var wire 1 # in1 $end
$var wire 1 ) out $end
$var wire 1 * s0 $end
$var wire 1 & select $end
$var wire 1 + w0 $end
$var wire 1 , w1 $end
$upscope $end
$scope module a2 $end
$var wire 1 $ in0 $end
$var wire 1 % in1 $end
$var wire 1 ( out $end
$var wire 1 - s0 $end
$var wire 1 & select $end
$var wire 1 . w0 $end
$var wire 1 / w1 $end
$upscope $end
$scope module output_1 $end
$var wire 1 ) in0 $end
$var wire 1 ( in1 $end
$var wire 1 ! out $end
$var wire 1 0 s0 $end
$var wire 1 ' select $end
$var wire 1 1 w0 $end
$var wire 1 2 w1 $end
$upscope $end
$upscope $end
$upscope $end
$enddefinitions $end
#0
$dumpvars
02
01
10
0/
0.
1-
0,
0+
1*
0)
0(
0'
0&
0%
0$
0#
0"
0!
$end
#10
00
1'
#20
10
0*
0-
0'
1&
#30
00
1'
#40
10
1*
1-
0'
0&
1%
#50
00
1'
#60
1(
10
0*
0-
1/
0'
1&
#70
1!
00
12
1'
#80
0!
1.
1(
10
02
1*
1-
0/
0'
0&
0%
1$
#90
1!
00
12
1'
#100
0(
0!
0.
10
02
0*
0-
0'
1&
#110
00
1'
#120
1(
1.
10
1*
1-
0'
0&
1%
#130
1!
00
12
1'
#140
0!
0.
10
02
0*
0-
1/
0'
1&
#150
1!
00
12
1'
#160
0!
0(
10
02
1*
1-
0/
0'
0&
0%
0$
1#
#170
00
1'
#180
1!
11
1)
10
0*
1,
0-
0'
1&
#190
0!
01
00
1'
#200
0)
10
1*
0,
1-
0'
0&
1%
#210
00
1'
#220
1!
11
1)
1(
10
0*
1,
0-
1/
0'
1&
#230
01
00
12
1'
#240
0!
0)
1.
1(
10
02
1*
0,
1-
0/
0'
0&
0%
1$
#250
1!
00
12
1'
#260
0(
11
1!
1)
0.
10
02
0*
1,
0-
0'
1&
#270
0!
01
00
1'
#280
1(
0)
1.
10
1*
0,
1-
0'
0&
1%
#290
1!
00
12
1'
#300
11
1!
1)
0.
10
02
0*
1,
0-
1/
0'
1&
#310
01
00
12
1'
#320
11
1!
1+
0(
1)
10
02
1*
1-
0/
0,
0'
0&
0%
0$
0#
1"
#330
0!
01
00
1'
#340
0!
0)
01
0+
10
0*
0-
0'
1&
#350
00
1'
#360
1!
11
1)
1+
10
1*
1-
0'
0&
1%
#370
0!
01
00
1'
#380
0!
0)
01
0+
1(
10
0*
0-
1/
0'
1&
#390
1!
00
12
1'
#400
11
1)
1!
1+
1.
1(
10
02
1*
1-
0/
0'
0&
0%
1$
#410
01
00
12
1'
#420
0)
0(
01
0!
0+
0.
10
02
0*
0-
0'
1&
#430
00
1'
#440
1!
11
1)
1(
1+
1.
10
1*
1-
0'
0&
1%
#450
01
00
12
1'
#460
0)
01
0!
0+
0.
10
02
0*
0-
1/
0'
1&
#470
1!
00
12
1'
#480
11
1)
1!
1+
0(
10
02
1*
1-
0/
0'
0&
0%
0$
1#
#490
0!
01
00
1'
#500
1!
11
0+
10
0*
1,
0-
0'
1&
#510
0!
01
00
1'
#520
1!
11
1+
1)
10
1*
0,
1-
0'
0&
1%
#530
0!
01
00
1'
#540
1!
11
0+
1(
10
0*
1,
0-
1/
0'
1&
#550
01
00
12
1'
#560
11
1!
1+
1)
1.
1(
10
02
1*
0,
1-
0/
0'
0&
0%
1$
#570
01
00
12
1'
#580
0(
11
1!
0+
0.
10
02
0*
1,
0-
0'
1&
#590
0!
01
00
1'
#600
1!
11
1(
1+
1)
1.
10
1*
0,
1-
0'
0&
1%
#610
01
00
12
1'
#620
11
1!
0+
0.
10
02
0*
1,
0-
1/
0'
1&
#630
01
00
12
1'
