mux2.v
module mux2(in0,in1,select,out);
	input in0,in1,select;
	output out;
	wire s0,w0,w1;

	not n1(s0,select);
	and a1(w0,s0,in0);
	and a2(w1,select,in1);
	or g3(out,w0,w1);
endmodule

mux2_tb.v
module tb_mux;
	reg data_in_0;
	reg data_in_1;
	reg sel;
	wire data_out;
	mux2 namexyz(data_in_0,data_in_1,sel,data_out);
	initial
	begin
		$dumpfile("mux_out.vcd");
		$dumpvars(0,tb_mux);
		data_in_0=0;
		data_in_1=0;
		sel=0;
		#50;

		data_in_0=0;	data_in_1=0;	sel=1;	#10;
		data_in_0=0;	data_in_1=1;	sel=0;	#10;
		data_in_0=0;	data_in_1=1;	sel=1;	#10;
		data_in_0=1;	data_in_1=0;	sel=0;	#10;
		data_in_0=1;	data_in_1=0;	sel=1;	#10;
		data_in_0=1;	data_in_1=1;	sel=0;	#10;
		data_in_0=1;	data_in_1=1;	sel=1;	#10;
	end
	endmodule

mux_out.vcd
$date
	Fri Jan 20 13:15:43 2023
$end
$version
	Icarus Verilog
$end
$timescale
	1s
$end
$scope module tb_mux $end
$var wire 1 ! data_out $end
$var reg 1 " data_in_0 $end
$var reg 1 # data_in_1 $end
$var reg 1 $ sel $end
$scope module namexyz $end
$var wire 1 " in0 $end
$var wire 1 # in1 $end
$var wire 1 ! out $end
$var wire 1 % s0 $end
$var wire 1 $ select $end
$var wire 1 & w0 $end
$var wire 1 ' w1 $end
$upscope $end
$upscope $end
$enddefinitions $end
#0
$dumpvars
0'
0&
1%
0$
0#
0"
0!
$end
#50
0%
1$
#60
1%
0$
1#
#70
1!
0%
1'
1$
#80
1&
1!
1%
0'
0$
0#
1"
#90
0!
0&
0%
1$
#100
1!
1&
1%
0$
1#
#110
0&
0%
1'
1$
